setup.cfg
setup.py
MakoLang.egg-info/PKG-INFO
MakoLang.egg-info/SOURCES.txt
MakoLang.egg-info/dependency_links.txt
MakoLang.egg-info/entry_points.txt
MakoLang.egg-info/requires.txt
MakoLang.egg-info/top_level.txt
makolang/__init__.py
