Metadata-Version: 1.0
Name: MakoLang
Version: 0.1.dev-r972
Summary: This package adds preprocessor to mako for convenient syntax of gettext strings, and babel extractor to process such templates.
Home-page: http://www.mr-pc.kiev.ua/en/projects/MakoLang
Author: Paul Colomiets
Author-email: pc@gafol.net
License: MIT
Keywords: mako templates gettext i18n l10n
Platform: UNKNOWN
